chloop/__init__.py
chloop-0.2.24.dist-info/LICENSE.txt
chloop-0.2.24.dist-info/METADATA
chloop-0.2.24.dist-info/WHEEL
chloop-0.2.24.dist-info/top_level.txt
chloop-0.2.24.dist-info/RECORD
