Metadata-Version: 2.1
Name: chloop
Version: 0.2.24
Summary: A Redis-backed REPL that saves command history, output, & errors
Home-page: https://github.com/kenjyco/chloop
Download-URL: https://github.com/kenjyco/chloop/tarball/v0.2.24
Author: Ken
Author-email: kenjyco@gmail.com
License: MIT
Keywords: repl,redis,cli,command-line,command,history,kenjyco
Platform: UNKNOWN
Classifier: Development Status :: 4 - Beta
Classifier: Environment :: Console
Classifier: Intended Audience :: Developers
Classifier: License :: OSI Approved :: MIT License
Classifier: Operating System :: MacOS :: MacOS X
Classifier: Operating System :: POSIX :: Linux
Classifier: Programming Language :: Python :: 3.5
Classifier: Programming Language :: Python :: 3.6
Classifier: Programming Language :: Python :: 3.7
Classifier: Programming Language :: Python :: 3.8
Classifier: Programming Language :: Python :: 3.9
Classifier: Programming Language :: Python :: 3.10
Classifier: Programming Language :: Python :: 3.11
Classifier: Programming Language :: Python :: 3.12
Classifier: Programming Language :: Python :: 3.13
Classifier: Programming Language :: Python
Classifier: Topic :: Software Development :: Libraries
Classifier: Topic :: Terminals
License-File: LICENSE.txt
Requires-Dist: bg-helper
Requires-Dist: click (>=6.0)
Requires-Dist: fs-helper
Requires-Dist: redis-helper
